{
  "title": "Поведінка та правила",
  "description": "Писані та неписані правила на робочому місці",
  "lessons": [
    {
      "id": "hygiene-gum-perfume",
      "title": "Жувальна гумка та парфуми – Заборонено на виробництві",
      "icon": "🚫",
      "sections": [
        {
          "type": "alert",
          "style": "warning",
          "text": "Було помічено використання жувальної гумки та парфумів на виробництві. Це заборонено відповідно до правил гігієни компанії."
        },
        {
          "type": "icon-row",
          "icons": [
            { "src": "/icons/no-gum.svg", "alt": "Жувальна гумка заборонена" },
            { "src": "/icons/no-perfume.svg", "alt": "Парфуми заборонені" }
          ]
        },
        {
          "type": "rules",
          "title": "У виробничих зонах суворо заборонено:",
          "items": [
            "Жувальна гумка, цукерки та м'ятні льодяники",
            "Парфуми та ароматизовані засоби"
          ]
        },
        {
          "type": "info",
          "title": "Це важливо для забезпечення:",
          "items": [
            "🍽️ Безпеки харчових продуктів",
            "🧼 Гігієни",
            "🛡️ Безпечного робочого середовища"
          ]
        },
        {
          "type": "alert",
          "style": "danger",
          "text": "Усі працівники повинні дотримуватися цих правил без винятку!"
        }
      ]
    }
  ]
}